{
  "tenantId": "od.phulbani",
  "moduleName": "TradeLicense",
  "TemporaryTradeType": [
    {
      "code": "NONEATINGNONMEDICALESTABLISHMENTS.TST316",
      "name": "Heavy Machinery",
      "uom": "NUMBEROFDAYS",
      "uomDescription": "Number of Days",
      "applicationDocument": [
        {
          "applicationType": "NEW",
          "documentList": [
            "OWNERIDPROOF",
            "OWNERSHIPPROOF",
            "OWNERPHOTO"
          ]
        },
        {
          "applicationType": "RENEWAL",
          "documentList": [
            "OWNERIDPROOF",
            "OWNERSHIPPROOF",
            "OWNERPHOTO",
            "OLDLICENCENO"
          ]
        }
      ],
      "verificationDocument": [],
      "active": true,
      "type": "TL",
      "validityPeriod": null
    },
    {
      "code": "NONEATINGNONMEDICALESTABLISHMENTS.TST272",
      "name": "Chitralaya",
      "uom": "NUMBEROFDAYS",
      "uomDescription": "Number of Days",
      "applicationDocument": [
        {
          "applicationType": "NEW",
          "documentList": [
            "OWNERIDPROOF",
            "OWNERSHIPPROOF",
            "OWNERPHOTO"
          ]
        },
        {
          "applicationType": "RENEWAL",
          "documentList": [
            "OWNERIDPROOF",
            "OWNERSHIPPROOF",
            "OWNERPHOTO",
            "OLDLICENCENO"
          ]
        }
      ],
      "verificationDocument": [],
      "active": true,
      "type": "TL",
      "validityPeriod": null
    },
    {
      "code": "NONEATINGNONMEDICALESTABLISHMENTS.TST444",
      "name": "Water bottle dealer Shop",
      "uom": "NUMBEROFDAYS",
      "uomDescription": "Number of Days",
      "applicationDocument": [
        {
          "applicationType": "NEW",
          "documentList": [
            "OWNERIDPROOF",
            "OWNERSHIPPROOF",
            "OWNERPHOTO"
          ]
        },
        {
          "applicationType": "RENEWAL",
          "documentList": [
            "OWNERIDPROOF",
            "OWNERSHIPPROOF",
            "OWNERPHOTO",
            "OLDLICENCENO"
          ]
        }
      ],
      "verificationDocument": [],
      "active": true,
      "type": "TL",
      "validityPeriod": null
    },
    {
      "code": "NONEATINGNONMEDICALESTABLISHMENTS.TST381",
      "name": "Sale Forest Products",
      "uom": "NUMBEROFDAYS",
      "uomDescription": "Number of Days",
      "applicationDocument": [
        {
          "applicationType": "NEW",
          "documentList": [
            "OWNERIDPROOF",
            "OWNERSHIPPROOF",
            "OWNERPHOTO"
          ]
        },
        {
          "applicationType": "RENEWAL",
          "documentList": [
            "OWNERIDPROOF",
            "OWNERSHIPPROOF",
            "OWNERPHOTO",
            "OLDLICENCENO"
          ]
        }
      ],
      "verificationDocument": [],
      "active": true,
      "type": "TL",
      "validityPeriod": null
    },
    {
      "code": "NONEATINGNONMEDICALESTABLISHMENTS.TST425",
      "name": "Trolley or Pulling Cart",
      "uom": "NUMBEROFDAYS",
      "uomDescription": "Number of Days",
      "applicationDocument": [
        {
          "applicationType": "NEW",
          "documentList": [
            "OWNERIDPROOF",
            "OWNERSHIPPROOF",
            "OWNERPHOTO"
          ]
        },
        {
          "applicationType": "RENEWAL",
          "documentList": [
            "OWNERIDPROOF",
            "OWNERSHIPPROOF",
            "OWNERPHOTO",
            "OLDLICENCENO"
          ]
        }
      ],
      "verificationDocument": [],
      "active": true,
      "type": "TL",
      "validityPeriod": null
    },
    {
      "code": "NONEATINGNONMEDICALESTABLISHMENTS.TST291",
      "name": "Dyes, Colours, pigments or powder etc",
      "uom": "NUMBEROFDAYS",
      "uomDescription": "Number of Days",
      "applicationDocument": [
        {
          "applicationType": "NEW",
          "documentList": [
            "OWNERIDPROOF",
            "OWNERSHIPPROOF",
            "OWNERPHOTO"
          ]
        },
        {
          "applicationType": "RENEWAL",
          "documentList": [
            "OWNERIDPROOF",
            "OWNERSHIPPROOF",
            "OWNERPHOTO",
            "OLDLICENCENO"
          ]
        }
      ],
      "verificationDocument": [],
      "active": true,
      "type": "TL",
      "validityPeriod": null
    },
    {
      "code": "NONEATINGNONMEDICALESTABLISHMENTS.TST287",
      "name": "Dice Workshop",
      "uom": "NUMBEROFDAYS",
      "uomDescription": "Number of Days",
      "applicationDocument": [
        {
          "applicationType": "NEW",
          "documentList": [
            "OWNERIDPROOF",
            "OWNERSHIPPROOF",
            "OWNERPHOTO"
          ]
        },
        {
          "applicationType": "RENEWAL",
          "documentList": [
            "OWNERIDPROOF",
            "OWNERSHIPPROOF",
            "OWNERPHOTO",
            "OLDLICENCENO"
          ]
        }
      ],
      "verificationDocument": [],
      "active": true,
      "type": "TL",
      "validityPeriod": null
    },
    {
      "code": "NONEATINGNONMEDICALESTABLISHMENTS.TST255",
      "name": "Bedding, Blankets, Cushions",
      "uom": "NUMBEROFDAYS",
      "uomDescription": "Number of Days",
      "applicationDocument": [
        {
          "applicationType": "NEW",
          "documentList": [
            "OWNERIDPROOF",
            "OWNERSHIPPROOF",
            "OWNERPHOTO"
          ]
        },
        {
          "applicationType": "RENEWAL",
          "documentList": [
            "OWNERIDPROOF",
            "OWNERSHIPPROOF",
            "OWNERPHOTO",
            "OLDLICENCENO"
          ]
        }
      ],
      "verificationDocument": [],
      "active": true,
      "type": "TL",
      "validityPeriod": null
    },
    {
      "code": "NONEATINGNONMEDICALESTABLISHMENTS.TST348",
      "name": "News press",
      "uom": "NUMBEROFDAYS",
      "uomDescription": "Number of Days",
      "applicationDocument": [
        {
          "applicationType": "NEW",
          "documentList": [
            "OWNERIDPROOF",
            "OWNERSHIPPROOF",
            "OWNERPHOTO"
          ]
        },
        {
          "applicationType": "RENEWAL",
          "documentList": [
            "OWNERIDPROOF",
            "OWNERSHIPPROOF",
            "OWNERPHOTO",
            "OLDLICENCENO"
          ]
        }
      ],
      "verificationDocument": [],
      "active": true,
      "type": "TL",
      "validityPeriod": null
    },
    {
      "code": "NONEATINGNONMEDICALESTABLISHMENTS.TST322",
      "name": "Ink for Printing writing or Stamping",
      "uom": "NUMBEROFDAYS",
      "uomDescription": "Number of Days",
      "applicationDocument": [
        {
          "applicationType": "NEW",
          "documentList": [
            "OWNERIDPROOF",
            "OWNERSHIPPROOF",
            "OWNERPHOTO"
          ]
        },
        {
          "applicationType": "RENEWAL",
          "documentList": [
            "OWNERIDPROOF",
            "OWNERSHIPPROOF",
            "OWNERPHOTO",
            "OLDLICENCENO"
          ]
        }
      ],
      "verificationDocument": [],
      "active": true,
      "type": "TL",
      "validityPeriod": null
    },
    {
      "code": "NONEATINGNONMEDICALESTABLISHMENTS.TST251",
      "name": "Baby Food",
      "uom": "NUMBEROFDAYS",
      "uomDescription": "Number of Days",
      "applicationDocument": [
        {
          "applicationType": "NEW",
          "documentList": [
            "OWNERIDPROOF",
            "OWNERSHIPPROOF",
            "OWNERPHOTO"
          ]
        },
        {
          "applicationType": "RENEWAL",
          "documentList": [
            "OWNERIDPROOF",
            "OWNERSHIPPROOF",
            "OWNERPHOTO",
            "OLDLICENCENO"
          ]
        }
      ],
      "verificationDocument": [],
      "active": true,
      "type": "TL",
      "validityPeriod": null
    },
    {
      "code": "NONEATINGNONMEDICALESTABLISHMENTS.TST274",
      "name": "Clay Idol Making Firm",
      "uom": "NUMBEROFDAYS",
      "uomDescription": "Number of Days",
      "applicationDocument": [
        {
          "applicationType": "NEW",
          "documentList": [
            "OWNERIDPROOF",
            "OWNERSHIPPROOF",
            "OWNERPHOTO"
          ]
        },
        {
          "applicationType": "RENEWAL",
          "documentList": [
            "OWNERIDPROOF",
            "OWNERSHIPPROOF",
            "OWNERPHOTO",
            "OLDLICENCENO"
          ]
        }
      ],
      "verificationDocument": [],
      "active": true,
      "type": "TL",
      "validityPeriod": null
    },
    {
      "code": "NONEATINGNONMEDICALESTABLISHMENTS.TST289",
      "name": "Distributor (Per Item)",
      "uom": "NUMBEROFDAYS",
      "uomDescription": "Number of Days",
      "applicationDocument": [
        {
          "applicationType": "NEW",
          "documentList": [
            "OWNERIDPROOF",
            "OWNERSHIPPROOF",
            "OWNERPHOTO"
          ]
        },
        {
          "applicationType": "RENEWAL",
          "documentList": [
            "OWNERIDPROOF",
            "OWNERSHIPPROOF",
            "OWNERPHOTO",
            "OLDLICENCENO"
          ]
        }
      ],
      "verificationDocument": [],
      "active": true,
      "type": "TL",
      "validityPeriod": null
    },
    {
      "code": "NONEATINGNONMEDICALESTABLISHMENTS.TST407",
      "name": "Storage & Business of Turmeric",
      "uom": "NUMBEROFDAYS",
      "uomDescription": "Number of Days",
      "applicationDocument": [
        {
          "applicationType": "NEW",
          "documentList": [
            "OWNERIDPROOF",
            "OWNERSHIPPROOF",
            "OWNERPHOTO"
          ]
        },
        {
          "applicationType": "RENEWAL",
          "documentList": [
            "OWNERIDPROOF",
            "OWNERSHIPPROOF",
            "OWNERPHOTO",
            "OLDLICENCENO"
          ]
        }
      ],
      "verificationDocument": [],
      "active": true,
      "type": "TL",
      "validityPeriod": null
    },
    {
      "code": "NONEATINGNONMEDICALESTABLISHMENTS.TST323",
      "name": "Insecticide or disinfectants or deodorants",
      "uom": "NUMBEROFDAYS",
      "uomDescription": "Number of Days",
      "applicationDocument": [
        {
          "applicationType": "NEW",
          "documentList": [
            "OWNERIDPROOF",
            "OWNERSHIPPROOF",
            "OWNERPHOTO"
          ]
        },
        {
          "applicationType": "RENEWAL",
          "documentList": [
            "OWNERIDPROOF",
            "OWNERSHIPPROOF",
            "OWNERPHOTO",
            "OLDLICENCENO"
          ]
        }
      ],
      "verificationDocument": [],
      "active": true,
      "type": "TL",
      "validityPeriod": null
    },
    {
      "code": "NONEATINGNONMEDICALESTABLISHMENTS.TST283",
      "name": "Copper Smith",
      "uom": "NUMBEROFDAYS",
      "uomDescription": "Number of Days",
      "applicationDocument": [
        {
          "applicationType": "NEW",
          "documentList": [
            "OWNERIDPROOF",
            "OWNERSHIPPROOF",
            "OWNERPHOTO"
          ]
        },
        {
          "applicationType": "RENEWAL",
          "documentList": [
            "OWNERIDPROOF",
            "OWNERSHIPPROOF",
            "OWNERPHOTO",
            "OLDLICENCENO"
          ]
        }
      ],
      "verificationDocument": [],
      "active": true,
      "type": "TL",
      "validityPeriod": null
    },
    {
      "code": "NONEATINGNONMEDICALESTABLISHMENTS.TST306",
      "name": "Gas Agency",
      "uom": "NUMBEROFDAYS",
      "uomDescription": "Number of Days",
      "applicationDocument": [
        {
          "applicationType": "NEW",
          "documentList": [
            "OWNERIDPROOF",
            "OWNERSHIPPROOF",
            "OWNERPHOTO"
          ]
        },
        {
          "applicationType": "RENEWAL",
          "documentList": [
            "OWNERIDPROOF",
            "OWNERSHIPPROOF",
            "OWNERPHOTO",
            "OLDLICENCENO"
          ]
        }
      ],
      "verificationDocument": [],
      "active": true,
      "type": "TL",
      "validityPeriod": null
    },
    {
      "code": "NONEATINGNONMEDICALESTABLISHMENTS.TST297",
      "name": "Event Management",
      "uom": "NUMBEROFDAYS",
      "uomDescription": "Number of Days",
      "applicationDocument": [
        {
          "applicationType": "NEW",
          "documentList": [
            "OWNERIDPROOF",
            "OWNERSHIPPROOF",
            "OWNERPHOTO"
          ]
        },
        {
          "applicationType": "RENEWAL",
          "documentList": [
            "OWNERIDPROOF",
            "OWNERSHIPPROOF",
            "OWNERPHOTO",
            "OLDLICENCENO"
          ]
        }
      ],
      "verificationDocument": [],
      "active": true,
      "type": "TL",
      "validityPeriod": null
    },
    {
      "code": "NONEATINGNONMEDICALESTABLISHMENTS.TST254",
      "name": "Beauty Parlour Non A/C",
      "uom": "NUMBEROFDAYS",
      "uomDescription": "Number of Days",
      "applicationDocument": [
        {
          "applicationType": "NEW",
          "documentList": [
            "OWNERIDPROOF",
            "OWNERSHIPPROOF",
            "OWNERPHOTO"
          ]
        },
        {
          "applicationType": "RENEWAL",
          "documentList": [
            "OWNERIDPROOF",
            "OWNERSHIPPROOF",
            "OWNERPHOTO",
            "OLDLICENCENO"
          ]
        }
      ],
      "verificationDocument": [],
      "active": true,
      "type": "TL",
      "validityPeriod": null
    },
    {
      "code": "FLAMABLES.TST20",
      "name": "Anodising or Metalizing",
      "uom": "NUMBEROFDAYS",
      "uomDescription": "Number of Days",
      "applicationDocument": [
        {
          "applicationType": "NEW",
          "documentList": [
            "OWNERIDPROOF",
            "OWNERSHIPPROOF",
            "OWNERPHOTO"
          ]
        },
        {
          "applicationType": "RENEWAL",
          "documentList": [
            "OWNERIDPROOF",
            "OWNERSHIPPROOF",
            "OWNERPHOTO",
            "OLDLICENCENO"
          ]
        }
      ],
      "verificationDocument": [],
      "active": true,
      "type": "TL",
      "validityPeriod": null
    },
    {
      "code": "NONEATINGNONMEDICALESTABLISHMENTS.TST256",
      "name": "Bleaching Cloth",
      "uom": "NUMBEROFDAYS",
      "uomDescription": "Number of Days",
      "applicationDocument": [
        {
          "applicationType": "NEW",
          "documentList": [
            "OWNERIDPROOF",
            "OWNERSHIPPROOF",
            "OWNERPHOTO"
          ]
        },
        {
          "applicationType": "RENEWAL",
          "documentList": [
            "OWNERIDPROOF",
            "OWNERSHIPPROOF",
            "OWNERPHOTO",
            "OLDLICENCENO"
          ]
        }
      ],
      "verificationDocument": [],
      "active": true,
      "type": "TL",
      "validityPeriod": null
    },
    {
      "code": "NONEATINGNONMEDICALESTABLISHMENTS.TST325",
      "name": "Insurance Company",
      "uom": "NUMBEROFDAYS",
      "uomDescription": "Number of Days",
      "applicationDocument": [
        {
          "applicationType": "NEW",
          "documentList": [
            "OWNERIDPROOF",
            "OWNERSHIPPROOF",
            "OWNERPHOTO"
          ]
        },
        {
          "applicationType": "RENEWAL",
          "documentList": [
            "OWNERIDPROOF",
            "OWNERSHIPPROOF",
            "OWNERPHOTO",
            "OLDLICENCENO"
          ]
        }
      ],
      "verificationDocument": [],
      "active": true,
      "type": "TL",
      "validityPeriod": null
    },
    {
      "code": "FLAMABLES.TST21",
      "name": "Chemicals",
      "uom": "NUMBEROFDAYS",
      "uomDescription": "Number of Days",
      "applicationDocument": [
        {
          "applicationType": "NEW",
          "documentList": [
            "OWNERIDPROOF",
            "OWNERSHIPPROOF",
            "OWNERPHOTO"
          ]
        },
        {
          "applicationType": "RENEWAL",
          "documentList": [
            "OWNERIDPROOF",
            "OWNERSHIPPROOF",
            "OWNERPHOTO",
            "OLDLICENCENO"
          ]
        }
      ],
      "verificationDocument": [],
      "active": true,
      "type": "TL",
      "validityPeriod": null
    },
    {
      "code": "NONEATINGNONMEDICALESTABLISHMENTS.TST392",
      "name": "Saree Centre",
      "uom": "NUMBEROFDAYS",
      "uomDescription": "Number of Days",
      "applicationDocument": [
        {
          "applicationType": "NEW",
          "documentList": [
            "OWNERIDPROOF",
            "OWNERSHIPPROOF",
            "OWNERPHOTO"
          ]
        },
        {
          "applicationType": "RENEWAL",
          "documentList": [
            "OWNERIDPROOF",
            "OWNERSHIPPROOF",
            "OWNERPHOTO",
            "OLDLICENCENO"
          ]
        }
      ],
      "verificationDocument": [],
      "active": true,
      "type": "TL",
      "validityPeriod": null
    },
    {
      "code": "EATINGESTABLISHMENTS.TST33",
      "name": "Foreign Liquor Off Shop",
      "uom": "NUMBEROFDAYS",
      "uomDescription": "Number of Days",
      "applicationDocument": [
        {
          "applicationType": "NEW",
          "documentList": [
            "OWNERIDPROOF",
            "OWNERSHIPPROOF",
            "OWNERPHOTO"
          ]
        },
        {
          "applicationType": "RENEWAL",
          "documentList": [
            "OWNERIDPROOF",
            "OWNERSHIPPROOF",
            "OWNERPHOTO",
            "OLDLICENCENO"
          ]
        }
      ],
      "verificationDocument": [],
      "active": true,
      "type": "TL",
      "validityPeriod": null
    },
    {
      "code": "NONEATINGNONMEDICALESTABLISHMENTS.TST419",
      "name": "Ticket Booking Counter",
      "uom": "NUMBEROFDAYS",
      "uomDescription": "Number of Days",
      "applicationDocument": [
        {
          "applicationType": "NEW",
          "documentList": [
            "OWNERIDPROOF",
            "OWNERSHIPPROOF",
            "OWNERPHOTO"
          ]
        },
        {
          "applicationType": "RENEWAL",
          "documentList": [
            "OWNERIDPROOF",
            "OWNERSHIPPROOF",
            "OWNERPHOTO",
            "OLDLICENCENO"
          ]
        }
      ],
      "verificationDocument": [],
      "active": true,
      "type": "TL",
      "validityPeriod": null
    },
    {
      "code": "NONEATINGNONMEDICALESTABLISHMENTS.TST273",
      "name": "Civil Work Testing Laboratory",
      "uom": "NUMBEROFDAYS",
      "uomDescription": "Number of Days",
      "applicationDocument": [
        {
          "applicationType": "NEW",
          "documentList": [
            "OWNERIDPROOF",
            "OWNERSHIPPROOF",
            "OWNERPHOTO"
          ]
        },
        {
          "applicationType": "RENEWAL",
          "documentList": [
            "OWNERIDPROOF",
            "OWNERSHIPPROOF",
            "OWNERPHOTO",
            "OLDLICENCENO"
          ]
        }
      ],
      "verificationDocument": [],
      "active": true,
      "type": "TL",
      "validityPeriod": null
    },
    {
      "code": "NONEATINGNONMEDICALESTABLISHMENTS.TST313",
      "name": "Gold Loan Finance",
      "uom": "NUMBEROFDAYS",
      "uomDescription": "Number of Days",
      "applicationDocument": [
        {
          "applicationType": "NEW",
          "documentList": [
            "OWNERIDPROOF",
            "OWNERSHIPPROOF",
            "OWNERPHOTO"
          ]
        },
        {
          "applicationType": "RENEWAL",
          "documentList": [
            "OWNERIDPROOF",
            "OWNERSHIPPROOF",
            "OWNERPHOTO",
            "OLDLICENCENO"
          ]
        }
      ],
      "verificationDocument": [],
      "active": true,
      "type": "TL",
      "validityPeriod": null
    },
    {
      "code": "FLAMABLES.TST23",
      "name": "Fire Works (Crackers) Wholeseller",
      "uom": "NUMBEROFDAYS",
      "uomDescription": "Number of Days",
      "applicationDocument": [
        {
          "applicationType": "NEW",
          "documentList": [
            "OWNERIDPROOF",
            "OWNERSHIPPROOF",
            "OWNERPHOTO"
          ]
        },
        {
          "applicationType": "RENEWAL",
          "documentList": [
            "OWNERIDPROOF",
            "OWNERSHIPPROOF",
            "OWNERPHOTO",
            "OLDLICENCENO"
          ]
        }
      ],
      "verificationDocument": [],
      "active": true,
      "type": "TL",
      "validityPeriod": null
    },
    {
      "code": "NONEATINGNONMEDICALESTABLISHMENTS.TST275",
      "name": "Coal Depot",
      "uom": "NUMBEROFDAYS",
      "uomDescription": "Number of Days",
      "applicationDocument": [
        {
          "applicationType": "NEW",
          "documentList": [
            "OWNERIDPROOF",
            "OWNERSHIPPROOF",
            "OWNERPHOTO"
          ]
        },
        {
          "applicationType": "RENEWAL",
          "documentList": [
            "OWNERIDPROOF",
            "OWNERSHIPPROOF",
            "OWNERPHOTO",
            "OLDLICENCENO"
          ]
        }
      ],
      "verificationDocument": [],
      "active": true,
      "type": "TL",
      "validityPeriod": null
    },
    {
      "code": "NONEATINGNONMEDICALESTABLISHMENTS.TST292",
      "name": "E-commerce Business",
      "uom": "NUMBEROFDAYS",
      "uomDescription": "Number of Days",
      "applicationDocument": [
        {
          "applicationType": "NEW",
          "documentList": [
            "OWNERIDPROOF",
            "OWNERSHIPPROOF",
            "OWNERPHOTO"
          ]
        },
        {
          "applicationType": "RENEWAL",
          "documentList": [
            "OWNERIDPROOF",
            "OWNERSHIPPROOF",
            "OWNERPHOTO",
            "OLDLICENCENO"
          ]
        }
      ],
      "verificationDocument": [],
      "active": true,
      "type": "TL",
      "validityPeriod": null
    },
    {
      "code": "NONEATINGNONMEDICALESTABLISHMENTS.TST317",
      "name": "Helmet shop",
      "uom": "NUMBEROFDAYS",
      "uomDescription": "Number of Days",
      "applicationDocument": [
        {
          "applicationType": "NEW",
          "documentList": [
            "OWNERIDPROOF",
            "OWNERSHIPPROOF",
            "OWNERPHOTO"
          ]
        },
        {
          "applicationType": "RENEWAL",
          "documentList": [
            "OWNERIDPROOF",
            "OWNERSHIPPROOF",
            "OWNERPHOTO",
            "OLDLICENCENO"
          ]
        }
      ],
      "verificationDocument": [],
      "active": true,
      "type": "TL",
      "validityPeriod": null
    },
    {
      "code": "NONEATINGNONMEDICALESTABLISHMENTS.TST370",
      "name": "Puja Item Shop",
      "uom": "NUMBEROFDAYS",
      "uomDescription": "Number of Days",
      "applicationDocument": [
        {
          "applicationType": "NEW",
          "documentList": [
            "OWNERIDPROOF",
            "OWNERSHIPPROOF",
            "OWNERPHOTO"
          ]
        },
        {
          "applicationType": "RENEWAL",
          "documentList": [
            "OWNERIDPROOF",
            "OWNERSHIPPROOF",
            "OWNERPHOTO",
            "OLDLICENCENO"
          ]
        }
      ],
      "verificationDocument": [],
      "active": true,
      "type": "TL",
      "validityPeriod": null
    },
    {
      "code": "NONEATINGNONMEDICALESTABLISHMENTS.TST328",
      "name": "Invertor and Battery sale",
      "uom": "NUMBEROFDAYS",
      "uomDescription": "Number of Days",
      "applicationDocument": [
        {
          "applicationType": "NEW",
          "documentList": [
            "OWNERIDPROOF",
            "OWNERSHIPPROOF",
            "OWNERPHOTO"
          ]
        },
        {
          "applicationType": "RENEWAL",
          "documentList": [
            "OWNERIDPROOF",
            "OWNERSHIPPROOF",
            "OWNERPHOTO",
            "OLDLICENCENO"
          ]
        }
      ],
      "verificationDocument": [],
      "active": true,
      "type": "TL",
      "validityPeriod": null
    },
    {
      "code": "EATINGESTABLISHMENTS.TST29",
      "name": "Country Wine Shop (Bhati )",
      "uom": "NUMBEROFDAYS",
      "uomDescription": "Number of Days",
      "applicationDocument": [
        {
          "applicationType": "NEW",
          "documentList": [
            "OWNERIDPROOF",
            "OWNERSHIPPROOF",
            "OWNERPHOTO"
          ]
        },
        {
          "applicationType": "RENEWAL",
          "documentList": [
            "OWNERIDPROOF",
            "OWNERSHIPPROOF",
            "OWNERPHOTO",
            "OLDLICENCENO"
          ]
        }
      ],
      "verificationDocument": [],
      "active": true,
      "type": "TL",
      "validityPeriod": null
    },
    {
      "code": "NONEATINGNONMEDICALESTABLISHMENTS.TST329",
      "name": "Iron Rod (retailer)",
      "uom": "NUMBEROFDAYS",
      "uomDescription": "Number of Days",
      "applicationDocument": [
        {
          "applicationType": "NEW",
          "documentList": [
            "OWNERIDPROOF",
            "OWNERSHIPPROOF",
            "OWNERPHOTO"
          ]
        },
        {
          "applicationType": "RENEWAL",
          "documentList": [
            "OWNERIDPROOF",
            "OWNERSHIPPROOF",
            "OWNERPHOTO",
            "OLDLICENCENO"
          ]
        }
      ],
      "verificationDocument": [],
      "active": true,
      "type": "TL",
      "validityPeriod": null
    },
    {
      "code": "NONEATINGNONMEDICALESTABLISHMENTS.TST349",
      "name": "Non-Banking / Private Finance Company",
      "uom": "NUMBEROFDAYS",
      "uomDescription": "Number of Days",
      "applicationDocument": [
        {
          "applicationType": "NEW",
          "documentList": [
            "OWNERIDPROOF",
            "OWNERSHIPPROOF",
            "OWNERPHOTO"
          ]
        },
        {
          "applicationType": "RENEWAL",
          "documentList": [
            "OWNERIDPROOF",
            "OWNERSHIPPROOF",
            "OWNERPHOTO",
            "OLDLICENCENO"
          ]
        }
      ],
      "verificationDocument": [],
      "active": true,
      "type": "TL",
      "validityPeriod": null
    },
    {
      "code": "FLAMABLES.TST28",
      "name": "Petrol Pump",
      "uom": "NUMBEROFDAYS",
      "uomDescription": "Number of Days",
      "applicationDocument": [
        {
          "applicationType": "NEW",
          "documentList": [
            "OWNERIDPROOF",
            "OWNERSHIPPROOF",
            "OWNERPHOTO"
          ]
        },
        {
          "applicationType": "RENEWAL",
          "documentList": [
            "OWNERIDPROOF",
            "OWNERSHIPPROOF",
            "OWNERPHOTO",
            "OLDLICENCENO"
          ]
        }
      ],
      "verificationDocument": [],
      "active": true,
      "type": "TL",
      "validityPeriod": null
    },
    {
      "code": "NONEATINGNONMEDICALESTABLISHMENTS.TST253",
      "name": "Band Party",
      "uom": "NUMBEROFDAYS",
      "uomDescription": "Number of Days",
      "applicationDocument": [
        {
          "applicationType": "NEW",
          "documentList": [
            "OWNERIDPROOF",
            "OWNERSHIPPROOF",
            "OWNERPHOTO"
          ]
        },
        {
          "applicationType": "RENEWAL",
          "documentList": [
            "OWNERIDPROOF",
            "OWNERSHIPPROOF",
            "OWNERPHOTO",
            "OLDLICENCENO"
          ]
        }
      ],
      "verificationDocument": [],
      "active": true,
      "type": "TL",
      "validityPeriod": null
    },
    {
      "code": "FLAMABLES.TST29",
      "name": "Storing Petrol, Disel and Kerosene",
      "uom": "NUMBEROFDAYS",
      "uomDescription": "Number of Days",
      "applicationDocument": [
        {
          "applicationType": "NEW",
          "documentList": [
            "OWNERIDPROOF",
            "OWNERSHIPPROOF",
            "OWNERPHOTO"
          ]
        },
        {
          "applicationType": "RENEWAL",
          "documentList": [
            "OWNERIDPROOF",
            "OWNERSHIPPROOF",
            "OWNERPHOTO",
            "OLDLICENCENO"
          ]
        }
      ],
      "verificationDocument": [],
      "active": true,
      "type": "TL",
      "validityPeriod": null
    },
    {
      "code": "NONEATINGNONMEDICALESTABLISHMENTS.TST286",
      "name": "Departmental Store/General Store",
      "uom": "NUMBEROFDAYS",
      "uomDescription": "Number of Days",
      "applicationDocument": [
        {
          "applicationType": "NEW",
          "documentList": [
            "OWNERIDPROOF",
            "OWNERSHIPPROOF",
            "OWNERPHOTO"
          ]
        },
        {
          "applicationType": "RENEWAL",
          "documentList": [
            "OWNERIDPROOF",
            "OWNERSHIPPROOF",
            "OWNERPHOTO",
            "OLDLICENCENO"
          ]
        }
      ],
      "verificationDocument": [],
      "active": true,
      "type": "TL",
      "validityPeriod": null
    },
    {
      "code": "NONEATINGNONMEDICALESTABLISHMENTS.TST270",
      "name": "Ceramic Shop",
      "uom": "NUMBEROFDAYS",
      "uomDescription": "Number of Days",
      "applicationDocument": [
        {
          "applicationType": "NEW",
          "documentList": [
            "OWNERIDPROOF",
            "OWNERSHIPPROOF",
            "OWNERPHOTO"
          ]
        },
        {
          "applicationType": "RENEWAL",
          "documentList": [
            "OWNERIDPROOF",
            "OWNERSHIPPROOF",
            "OWNERPHOTO",
            "OLDLICENCENO"
          ]
        }
      ],
      "verificationDocument": [],
      "active": true,
      "type": "TL",
      "validityPeriod": null
    },
    {
      "code": "NONEATINGNONMEDICALESTABLISHMENTS.TST427",
      "name": "Tyre Repair Shop",
      "uom": "NUMBEROFDAYS",
      "uomDescription": "Number of Days",
      "applicationDocument": [
        {
          "applicationType": "NEW",
          "documentList": [
            "OWNERIDPROOF",
            "OWNERSHIPPROOF",
            "OWNERPHOTO"
          ]
        },
        {
          "applicationType": "RENEWAL",
          "documentList": [
            "OWNERIDPROOF",
            "OWNERSHIPPROOF",
            "OWNERPHOTO",
            "OLDLICENCENO"
          ]
        }
      ],
      "verificationDocument": [],
      "active": true,
      "type": "TL",
      "validityPeriod": null
    },
    {
      "code": "NONEATINGNONMEDICALESTABLISHMENTS.TST252",
      "name": "Bags/ Lugguage",
      "uom": "NUMBEROFDAYS",
      "uomDescription": "Number of Days",
      "applicationDocument": [
        {
          "applicationType": "NEW",
          "documentList": [
            "OWNERIDPROOF",
            "OWNERSHIPPROOF",
            "OWNERPHOTO"
          ]
        },
        {
          "applicationType": "RENEWAL",
          "documentList": [
            "OWNERIDPROOF",
            "OWNERSHIPPROOF",
            "OWNERPHOTO",
            "OLDLICENCENO"
          ]
        }
      ],
      "verificationDocument": [],
      "active": true,
      "type": "TL",
      "validityPeriod": null
    },
    {
      "code": "NONEATINGNONMEDICALESTABLISHMENTS.TST371",
      "name": "Rakhi Shop",
      "uom": "NUMBEROFDAYS",
      "uomDescription": "Number of Days",
      "applicationDocument": [
        {
          "applicationType": "NEW",
          "documentList": [
            "OWNERIDPROOF",
            "OWNERSHIPPROOF",
            "OWNERPHOTO"
          ]
        },
        {
          "applicationType": "RENEWAL",
          "documentList": [
            "OWNERIDPROOF",
            "OWNERSHIPPROOF",
            "OWNERPHOTO",
            "OLDLICENCENO"
          ]
        }
      ],
      "verificationDocument": [],
      "active": true,
      "type": "TL",
      "validityPeriod": null
    },
    {
      "code": "NONEATINGNONMEDICALESTABLISHMENTS.TST441",
      "name": "Utensil Shop",
      "uom": "NUMBEROFDAYS",
      "uomDescription": "Number of Days",
      "applicationDocument": [
        {
          "applicationType": "NEW",
          "documentList": [
            "OWNERIDPROOF",
            "OWNERSHIPPROOF",
            "OWNERPHOTO"
          ]
        },
        {
          "applicationType": "RENEWAL",
          "documentList": [
            "OWNERIDPROOF",
            "OWNERSHIPPROOF",
            "OWNERPHOTO",
            "OLDLICENCENO"
          ]
        }
      ],
      "verificationDocument": [],
      "active": true,
      "type": "TL",
      "validityPeriod": null
    },
    {
      "code": "NONEATINGNONMEDICALESTABLISHMENTS.TST278",
      "name": "Cold Storage",
      "uom": "NUMBEROFDAYS",
      "uomDescription": "Number of Days",
      "applicationDocument": [
        {
          "applicationType": "NEW",
          "documentList": [
            "OWNERIDPROOF",
            "OWNERSHIPPROOF",
            "OWNERPHOTO"
          ]
        },
        {
          "applicationType": "RENEWAL",
          "documentList": [
            "OWNERIDPROOF",
            "OWNERSHIPPROOF",
            "OWNERPHOTO",
            "OLDLICENCENO"
          ]
        }
      ],
      "verificationDocument": [],
      "active": true,
      "type": "TL",
      "validityPeriod": null
    },
    {
      "code": "EATINGESTABLISHMENTS.TST27",
      "name": "Café",
      "uom": "NUMBEROFDAYS",
      "uomDescription": "Number of Days",
      "applicationDocument": [
        {
          "applicationType": "NEW",
          "documentList": [
            "OWNERIDPROOF",
            "OWNERSHIPPROOF",
            "OWNERPHOTO"
          ]
        },
        {
          "applicationType": "RENEWAL",
          "documentList": [
            "OWNERIDPROOF",
            "OWNERSHIPPROOF",
            "OWNERPHOTO",
            "OLDLICENCENO"
          ]
        }
      ],
      "verificationDocument": [],
      "active": true,
      "type": "TL",
      "validityPeriod": null
    },
    {
      "code": "NONEATINGNONMEDICALESTABLISHMENTS.TST309",
      "name": "Glass / Glass Articles",
      "uom": "NUMBEROFDAYS",
      "uomDescription": "Number of Days",
      "applicationDocument": [
        {
          "applicationType": "NEW",
          "documentList": [
            "OWNERIDPROOF",
            "OWNERSHIPPROOF",
            "OWNERPHOTO"
          ]
        },
        {
          "applicationType": "RENEWAL",
          "documentList": [
            "OWNERIDPROOF",
            "OWNERSHIPPROOF",
            "OWNERPHOTO",
            "OLDLICENCENO"
          ]
        }
      ],
      "verificationDocument": [],
      "active": true,
      "type": "TL",
      "validityPeriod": null
    },
    {
      "code": "NONEATINGNONMEDICALESTABLISHMENTS.TST300",
      "name": "Flower Plant stall",
      "uom": "NUMBEROFDAYS",
      "uomDescription": "Number of Days",
      "applicationDocument": [
        {
          "applicationType": "NEW",
          "documentList": [
            "OWNERIDPROOF",
            "OWNERSHIPPROOF",
            "OWNERPHOTO"
          ]
        },
        {
          "applicationType": "RENEWAL",
          "documentList": [
            "OWNERIDPROOF",
            "OWNERSHIPPROOF",
            "OWNERPHOTO",
            "OLDLICENCENO"
          ]
        }
      ],
      "verificationDocument": [],
      "active": true,
      "type": "TL",
      "validityPeriod": null
    },
    {
      "code": "NONEATINGNONMEDICALESTABLISHMENTS.TST327",
      "name": "Internet Service Provider",
      "uom": "NUMBEROFDAYS",
      "uomDescription": "Number of Days",
      "applicationDocument": [
        {
          "applicationType": "NEW",
          "documentList": [
            "OWNERIDPROOF",
            "OWNERSHIPPROOF",
            "OWNERPHOTO"
          ]
        },
        {
          "applicationType": "RENEWAL",
          "documentList": [
            "OWNERIDPROOF",
            "OWNERSHIPPROOF",
            "OWNERPHOTO",
            "OLDLICENCENO"
          ]
        }
      ],
      "verificationDocument": [],
      "active": true,
      "type": "TL",
      "validityPeriod": null
    },
    {
      "code": "NONEATINGNONMEDICALESTABLISHMENTS.TST293",
      "name": "Electrical Items",
      "uom": "NUMBEROFDAYS",
      "uomDescription": "Number of Days",
      "applicationDocument": [
        {
          "applicationType": "NEW",
          "documentList": [
            "OWNERIDPROOF",
            "OWNERSHIPPROOF",
            "OWNERPHOTO"
          ]
        },
        {
          "applicationType": "RENEWAL",
          "documentList": [
            "OWNERIDPROOF",
            "OWNERSHIPPROOF",
            "OWNERPHOTO",
            "OLDLICENCENO"
          ]
        }
      ],
      "verificationDocument": [],
      "active": true,
      "type": "TL",
      "validityPeriod": null
    },
    {
      "code": "NONEATINGNONMEDICALESTABLISHMENTS.TST310",
      "name": "Glass fitting",
      "uom": "NUMBEROFDAYS",
      "uomDescription": "Number of Days",
      "applicationDocument": [
        {
          "applicationType": "NEW",
          "documentList": [
            "OWNERIDPROOF",
            "OWNERSHIPPROOF",
            "OWNERPHOTO"
          ]
        },
        {
          "applicationType": "RENEWAL",
          "documentList": [
            "OWNERIDPROOF",
            "OWNERSHIPPROOF",
            "OWNERPHOTO",
            "OLDLICENCENO"
          ]
        }
      ],
      "verificationDocument": [],
      "active": true,
      "type": "TL",
      "validityPeriod": null
    },
    {
      "code": "NONEATINGNONMEDICALESTABLISHMENTS.TST276",
      "name": "Coal Transport",
      "uom": "NUMBEROFDAYS",
      "uomDescription": "Number of Days",
      "applicationDocument": [
        {
          "applicationType": "NEW",
          "documentList": [
            "OWNERIDPROOF",
            "OWNERSHIPPROOF",
            "OWNERPHOTO"
          ]
        },
        {
          "applicationType": "RENEWAL",
          "documentList": [
            "OWNERIDPROOF",
            "OWNERSHIPPROOF",
            "OWNERPHOTO",
            "OLDLICENCENO"
          ]
        }
      ],
      "verificationDocument": [],
      "active": true,
      "type": "TL",
      "validityPeriod": null
    },
    {
      "code": "NONEATINGNONMEDICALESTABLISHMENTS.TST282",
      "name": "Contract labour supplier/Manpower Service Provider",
      "uom": "NUMBEROFDAYS",
      "uomDescription": "Number of Days",
      "applicationDocument": [
        {
          "applicationType": "NEW",
          "documentList": [
            "OWNERIDPROOF",
            "OWNERSHIPPROOF",
            "OWNERPHOTO"
          ]
        },
        {
          "applicationType": "RENEWAL",
          "documentList": [
            "OWNERIDPROOF",
            "OWNERSHIPPROOF",
            "OWNERPHOTO",
            "OLDLICENCENO"
          ]
        }
      ],
      "verificationDocument": [],
      "active": true,
      "type": "TL",
      "validityPeriod": null
    },
    {
      "code": "NONEATINGNONMEDICALESTABLISHMENTS.TST247",
      "name": "Ashes",
      "uom": "NUMBEROFDAYS",
      "uomDescription": "Number of Days",
      "applicationDocument": [
        {
          "applicationType": "NEW",
          "documentList": [
            "OWNERIDPROOF",
            "OWNERSHIPPROOF",
            "OWNERPHOTO"
          ]
        },
        {
          "applicationType": "RENEWAL",
          "documentList": [
            "OWNERIDPROOF",
            "OWNERSHIPPROOF",
            "OWNERPHOTO",
            "OLDLICENCENO"
          ]
        }
      ],
      "verificationDocument": [],
      "active": true,
      "type": "TL",
      "validityPeriod": null
    },
    {
      "code": "NONEATINGNONMEDICALESTABLISHMENTS.TST248",
      "name": "Astrology/Vaastu",
      "uom": "NUMBEROFDAYS",
      "uomDescription": "Number of Days",
      "applicationDocument": [
        {
          "applicationType": "NEW",
          "documentList": [
            "OWNERIDPROOF",
            "OWNERSHIPPROOF",
            "OWNERPHOTO"
          ]
        },
        {
          "applicationType": "RENEWAL",
          "documentList": [
            "OWNERIDPROOF",
            "OWNERSHIPPROOF",
            "OWNERPHOTO",
            "OLDLICENCENO"
          ]
        }
      ],
      "verificationDocument": [],
      "active": true,
      "type": "TL",
      "validityPeriod": null
    },
    {
      "code": "NONEATINGNONMEDICALESTABLISHMENTS.TST249",
      "name": "ATM",
      "uom": "NUMBEROFDAYS",
      "uomDescription": "Number of Days",
      "applicationDocument": [
        {
          "applicationType": "NEW",
          "documentList": [
            "OWNERIDPROOF",
            "OWNERSHIPPROOF",
            "OWNERPHOTO"
          ]
        },
        {
          "applicationType": "RENEWAL",
          "documentList": [
            "OWNERIDPROOF",
            "OWNERSHIPPROOF",
            "OWNERPHOTO",
            "OLDLICENCENO"
          ]
        }
      ],
      "verificationDocument": [],
      "active": true,
      "type": "TL",
      "validityPeriod": null
    },
    {
      "code": "NONEATINGNONMEDICALESTABLISHMENTS.TST250",
      "name": "Automobile Garage",
      "uom": "NUMBEROFDAYS",
      "uomDescription": "Number of Days",
      "applicationDocument": [
        {
          "applicationType": "NEW",
          "documentList": [
            "OWNERIDPROOF",
            "OWNERSHIPPROOF",
            "OWNERPHOTO"
          ]
        },
        {
          "applicationType": "RENEWAL",
          "documentList": [
            "OWNERIDPROOF",
            "OWNERSHIPPROOF",
            "OWNERPHOTO",
            "OLDLICENCENO"
          ]
        }
      ],
      "verificationDocument": [],
      "active": true,
      "type": "TL",
      "validityPeriod": null
    },
    {
      "code": "EATINGESTABLISHMENTS.TST28",
      "name": "Country Liquor Shops",
      "uom": "NUMBEROFDAYS",
      "uomDescription": "Number of Days",
      "applicationDocument": [
        {
          "applicationType": "NEW",
          "documentList": [
            "OWNERIDPROOF",
            "OWNERSHIPPROOF",
            "OWNERPHOTO"
          ]
        },
        {
          "applicationType": "RENEWAL",
          "documentList": [
            "OWNERIDPROOF",
            "OWNERSHIPPROOF",
            "OWNERPHOTO",
            "OLDLICENCENO"
          ]
        }
      ],
      "verificationDocument": [],
      "active": true,
      "type": "TL",
      "validityPeriod": null
    },
    {
      "code": "EATINGESTABLISHMENTS.TST34",
      "name": "Manufacturing / Selling of Chocolate, Mixture & Biscuits",
      "uom": "NUMBEROFDAYS",
      "uomDescription": "Number of Days",
      "applicationDocument": [
        {
          "applicationType": "NEW",
          "documentList": [
            "OWNERIDPROOF",
            "OWNERSHIPPROOF",
            "OWNERPHOTO"
          ]
        },
        {
          "applicationType": "RENEWAL",
          "documentList": [
            "OWNERIDPROOF",
            "OWNERSHIPPROOF",
            "OWNERPHOTO",
            "OLDLICENCENO"
          ]
        }
      ],
      "verificationDocument": [],
      "active": true,
      "type": "TL",
      "validityPeriod": null
    },
    {
      "code": "NONEATINGNONMEDICALESTABLISHMENTS.TST277",
      "name": "Coconut Godown",
      "uom": "NUMBEROFDAYS",
      "uomDescription": "Number of Days",
      "applicationDocument": [
        {
          "applicationType": "NEW",
          "documentList": [
            "OWNERIDPROOF",
            "OWNERSHIPPROOF",
            "OWNERPHOTO"
          ]
        },
        {
          "applicationType": "RENEWAL",
          "documentList": [
            "OWNERIDPROOF",
            "OWNERSHIPPROOF",
            "OWNERPHOTO",
            "OLDLICENCENO"
          ]
        }
      ],
      "verificationDocument": [],
      "active": true,
      "type": "TL",
      "validityPeriod": null
    },
    {
      "code": "NONEATINGNONMEDICALESTABLISHMENTS.TST443",
      "name": "Ware Housing",
      "uom": "NUMBEROFDAYS",
      "uomDescription": "Number of Days",
      "applicationDocument": [
        {
          "applicationType": "NEW",
          "documentList": [
            "OWNERIDPROOF",
            "OWNERSHIPPROOF",
            "OWNERPHOTO"
          ]
        },
        {
          "applicationType": "RENEWAL",
          "documentList": [
            "OWNERIDPROOF",
            "OWNERSHIPPROOF",
            "OWNERPHOTO",
            "OLDLICENCENO"
          ]
        }
      ],
      "verificationDocument": [],
      "active": true,
      "type": "TL",
      "validityPeriod": null
    },
    {
      "code": "NONEATINGNONMEDICALESTABLISHMENTS.TST257",
      "name": "Blouse Centre",
      "uom": "NUMBEROFDAYS",
      "uomDescription": "Number of Days",
      "applicationDocument": [
        {
          "applicationType": "NEW",
          "documentList": [
            "OWNERIDPROOF",
            "OWNERSHIPPROOF",
            "OWNERPHOTO"
          ]
        },
        {
          "applicationType": "RENEWAL",
          "documentList": [
            "OWNERIDPROOF",
            "OWNERSHIPPROOF",
            "OWNERPHOTO",
            "OLDLICENCENO"
          ]
        }
      ],
      "verificationDocument": [],
      "active": true,
      "type": "TL",
      "validityPeriod": null
    },
    {
      "code": "NONEATINGNONMEDICALESTABLISHMENTS.TST220",
      "name": "Street Vendor",
      "uom": "NUMBEROFDAYS",
      "uomDescription": "Number of Days",
      "applicationDocument": [
        {
          "applicationType": "NEW",
          "documentList": [
            "OWNERIDPROOF",
            "OWNERSHIPPROOF",
            "OWNERPHOTO"
          ]
        },
        {
          "applicationType": "RENEWAL",
          "documentList": [
            "OWNERIDPROOF",
            "OWNERSHIPPROOF",
            "OWNERPHOTO",
            "OLDLICENCENO"
          ]
        }
      ],
      "verificationDocument": [],
      "active": true,
      "type": "TL",
      "validityPeriod": null
    },
    {
      "code": "SMALLSCALEINDUSTRIESSMALLMEDIUMFACTORIES.TST24",
      "name": "Coir Industry",
      "uom": "NUMBEROFDAYS",
      "uomDescription": "Number of Days",
      "applicationDocument": [
        {
          "applicationType": "NEW",
          "documentList": [
            "OWNERIDPROOF",
            "OWNERSHIPPROOF",
            "OWNERPHOTO"
          ]
        },
        {
          "applicationType": "RENEWAL",
          "documentList": [
            "OWNERIDPROOF",
            "OWNERSHIPPROOF",
            "OWNERPHOTO",
            "OLDLICENCENO"
          ]
        }
      ],
      "verificationDocument": [],
      "active": true,
      "type": "TL",
      "validityPeriod": null
    },
    {
      "code": "NONEATINGNONMEDICALESTABLISHMENTS.TST263",
      "name": "Bus Ticket Counter",
      "uom": "NUMBEROFDAYS",
      "uomDescription": "Number of Days",
      "applicationDocument": [
        {
          "applicationType": "NEW",
          "documentList": [
            "OWNERIDPROOF",
            "OWNERSHIPPROOF",
            "OWNERPHOTO"
          ]
        },
        {
          "applicationType": "RENEWAL",
          "documentList": [
            "OWNERIDPROOF",
            "OWNERSHIPPROOF",
            "OWNERPHOTO",
            "OLDLICENCENO"
          ]
        }
      ],
      "verificationDocument": [],
      "active": true,
      "type": "TL",
      "validityPeriod": null
    },
    {
      "code": "NONEATINGNONMEDICALESTABLISHMENTS.TST269",
      "name": "Celluloid or celluloid goods",
      "uom": "NUMBEROFDAYS",
      "uomDescription": "Number of Days",
      "applicationDocument": [
        {
          "applicationType": "NEW",
          "documentList": [
            "OWNERIDPROOF",
            "OWNERSHIPPROOF",
            "OWNERPHOTO"
          ]
        },
        {
          "applicationType": "RENEWAL",
          "documentList": [
            "OWNERIDPROOF",
            "OWNERSHIPPROOF",
            "OWNERPHOTO",
            "OLDLICENCENO"
          ]
        }
      ],
      "verificationDocument": [],
      "active": true,
      "type": "TL",
      "validityPeriod": null
    },
    {
      "code": "NONEATINGNONMEDICALESTABLISHMENTS.TST268",
      "name": "Cartridge Filling",
      "uom": "NUMBEROFDAYS",
      "uomDescription": "Number of Days",
      "applicationDocument": [
        {
          "applicationType": "NEW",
          "documentList": [
            "OWNERIDPROOF",
            "OWNERSHIPPROOF",
            "OWNERPHOTO"
          ]
        },
        {
          "applicationType": "RENEWAL",
          "documentList": [
            "OWNERIDPROOF",
            "OWNERSHIPPROOF",
            "OWNERPHOTO",
            "OLDLICENCENO"
          ]
        }
      ],
      "verificationDocument": [],
      "active": true,
      "type": "TL",
      "validityPeriod": null
    },
    {
      "code": "NONEATINGNONMEDICALESTABLISHMENTS.TST445",
      "name": "Water Packaging and Selling",
      "uom": "NUMBEROFDAYS",
      "uomDescription": "Number of Days",
      "applicationDocument": [
        {
          "applicationType": "NEW",
          "documentList": [
            "OWNERIDPROOF",
            "OWNERSHIPPROOF",
            "OWNERPHOTO"
          ]
        },
        {
          "applicationType": "RENEWAL",
          "documentList": [
            "OWNERIDPROOF",
            "OWNERSHIPPROOF",
            "OWNERPHOTO",
            "OLDLICENCENO"
          ]
        }
      ],
      "verificationDocument": [],
      "active": true,
      "type": "TL",
      "validityPeriod": null
    },
    {
      "code": "NONEATINGNONMEDICALESTABLISHMENTS.TST376",
      "name": "Road way Transport",
      "uom": "NUMBEROFDAYS",
      "uomDescription": "Number of Days",
      "applicationDocument": [
        {
          "applicationType": "NEW",
          "documentList": [
            "OWNERIDPROOF",
            "OWNERSHIPPROOF",
            "OWNERPHOTO"
          ]
        },
        {
          "applicationType": "RENEWAL",
          "documentList": [
            "OWNERIDPROOF",
            "OWNERSHIPPROOF",
            "OWNERPHOTO",
            "OLDLICENCENO"
          ]
        }
      ],
      "verificationDocument": [],
      "active": true,
      "type": "TL",
      "validityPeriod": null
    },
    {
      "code": "NONEATINGNONMEDICALESTABLISHMENTS.TST330",
      "name": "Iron Rod (wholesaler)",
      "uom": "NUMBEROFDAYS",
      "uomDescription": "Number of Days",
      "applicationDocument": [
        {
          "applicationType": "NEW",
          "documentList": [
            "OWNERIDPROOF",
            "OWNERSHIPPROOF",
            "OWNERPHOTO"
          ]
        },
        {
          "applicationType": "RENEWAL",
          "documentList": [
            "OWNERIDPROOF",
            "OWNERSHIPPROOF",
            "OWNERPHOTO",
            "OLDLICENCENO"
          ]
        }
      ],
      "verificationDocument": [],
      "active": true,
      "type": "TL",
      "validityPeriod": null
    },
    {
      "code": "EATINGESTABLISHMENTS.TST32",
      "name": "Foreign Liquor Distributor",
      "uom": "NUMBEROFDAYS",
      "uomDescription": "Number of Days",
      "applicationDocument": [
        {
          "applicationType": "NEW",
          "documentList": [
            "OWNERIDPROOF",
            "OWNERSHIPPROOF",
            "OWNERPHOTO"
          ]
        },
        {
          "applicationType": "RENEWAL",
          "documentList": [
            "OWNERIDPROOF",
            "OWNERSHIPPROOF",
            "OWNERPHOTO",
            "OLDLICENCENO"
          ]
        }
      ],
      "verificationDocument": [],
      "active": true,
      "type": "TL",
      "validityPeriod": null
    },
    {
      "code": "NONEATINGNONMEDICALESTABLISHMENTS.TST281",
      "name": "Consultancy Management",
      "uom": "NUMBEROFDAYS",
      "uomDescription": "Number of Days",
      "applicationDocument": [
        {
          "applicationType": "NEW",
          "documentList": [
            "OWNERIDPROOF",
            "OWNERSHIPPROOF",
            "OWNERPHOTO"
          ]
        },
        {
          "applicationType": "RENEWAL",
          "documentList": [
            "OWNERIDPROOF",
            "OWNERSHIPPROOF",
            "OWNERPHOTO",
            "OLDLICENCENO"
          ]
        }
      ],
      "verificationDocument": [],
      "active": true,
      "type": "TL",
      "validityPeriod": null
    },
    {
      "code": "NONEATINGNONMEDICALESTABLISHMENTS.TST294",
      "name": "Electroplating",
      "uom": "NUMBEROFDAYS",
      "uomDescription": "Number of Days",
      "applicationDocument": [
        {
          "applicationType": "NEW",
          "documentList": [
            "OWNERIDPROOF",
            "OWNERSHIPPROOF",
            "OWNERPHOTO"
          ]
        },
        {
          "applicationType": "RENEWAL",
          "documentList": [
            "OWNERIDPROOF",
            "OWNERSHIPPROOF",
            "OWNERPHOTO",
            "OLDLICENCENO"
          ]
        }
      ],
      "verificationDocument": [],
      "active": true,
      "type": "TL",
      "validityPeriod": null
    },
    {
      "code": "NONEATINGNONMEDICALESTABLISHMENTS.TST428",
      "name": "Tyre showroom",
      "uom": "NUMBEROFDAYS",
      "uomDescription": "Number of Days",
      "applicationDocument": [
        {
          "applicationType": "NEW",
          "documentList": [
            "OWNERIDPROOF",
            "OWNERSHIPPROOF",
            "OWNERPHOTO"
          ]
        },
        {
          "applicationType": "RENEWAL",
          "documentList": [
            "OWNERIDPROOF",
            "OWNERSHIPPROOF",
            "OWNERPHOTO",
            "OLDLICENCENO"
          ]
        }
      ],
      "verificationDocument": [],
      "active": true,
      "type": "TL",
      "validityPeriod": null
    },
    {
      "code": "NONEATINGNONMEDICALESTABLISHMENTS.TST267",
      "name": "Car Rental",
      "uom": "NUMBEROFDAYS",
      "uomDescription": "Number of Days",
      "applicationDocument": [
        {
          "applicationType": "NEW",
          "documentList": [
            "OWNERIDPROOF",
            "OWNERSHIPPROOF",
            "OWNERPHOTO"
          ]
        },
        {
          "applicationType": "RENEWAL",
          "documentList": [
            "OWNERIDPROOF",
            "OWNERSHIPPROOF",
            "OWNERPHOTO",
            "OLDLICENCENO"
          ]
        }
      ],
      "verificationDocument": [],
      "active": true,
      "type": "TL",
      "validityPeriod": null
    },
    {
      "code": "NONEATINGNONMEDICALESTABLISHMENTS.TST284",
      "name": "Cotton Thread goods",
      "uom": "NUMBEROFDAYS",
      "uomDescription": "Number of Days",
      "applicationDocument": [
        {
          "applicationType": "NEW",
          "documentList": [
            "OWNERIDPROOF",
            "OWNERSHIPPROOF",
            "OWNERPHOTO"
          ]
        },
        {
          "applicationType": "RENEWAL",
          "documentList": [
            "OWNERIDPROOF",
            "OWNERSHIPPROOF",
            "OWNERPHOTO",
            "OLDLICENCENO"
          ]
        }
      ],
      "verificationDocument": [],
      "active": true,
      "type": "TL",
      "validityPeriod": null
    },
    {
      "code": "SMALLSCALEINDUSTRIESSMALLMEDIUMFACTORIES.TST23",
      "name": "Braiding or Plating for manufacturing of tapes/ropes/shoe laces etc",
      "uom": "NUMBEROFDAYS",
      "uomDescription": "Number of Days",
      "applicationDocument": [
        {
          "applicationType": "NEW",
          "documentList": [
            "OWNERIDPROOF",
            "OWNERSHIPPROOF",
            "OWNERPHOTO"
          ]
        },
        {
          "applicationType": "RENEWAL",
          "documentList": [
            "OWNERIDPROOF",
            "OWNERSHIPPROOF",
            "OWNERPHOTO",
            "OLDLICENCENO"
          ]
        }
      ],
      "verificationDocument": [],
      "active": true,
      "type": "TL",
      "validityPeriod": null
    },
    {
      "code": "NONEATINGNONMEDICALESTABLISHMENTS.TST315",
      "name": "Gudakhu",
      "uom": "NUMBEROFDAYS",
      "uomDescription": "Number of Days",
      "applicationDocument": [
        {
          "applicationType": "NEW",
          "documentList": [
            "OWNERIDPROOF",
            "OWNERSHIPPROOF",
            "OWNERPHOTO"
          ]
        },
        {
          "applicationType": "RENEWAL",
          "documentList": [
            "OWNERIDPROOF",
            "OWNERSHIPPROOF",
            "OWNERPHOTO",
            "OLDLICENCENO"
          ]
        }
      ],
      "verificationDocument": [],
      "active": true,
      "type": "TL",
      "validityPeriod": null
    },
    {
      "code": "NONEATINGNONMEDICALESTABLISHMENTS.TST258",
      "name": "Bolbam",
      "uom": "NUMBEROFDAYS",
      "uomDescription": "Number of Days",
      "applicationDocument": [
        {
          "applicationType": "NEW",
          "documentList": [
            "OWNERIDPROOF",
            "OWNERSHIPPROOF",
            "OWNERPHOTO"
          ]
        },
        {
          "applicationType": "RENEWAL",
          "documentList": [
            "OWNERIDPROOF",
            "OWNERSHIPPROOF",
            "OWNERPHOTO",
            "OLDLICENCENO"
          ]
        }
      ],
      "verificationDocument": [],
      "active": true,
      "type": "TL",
      "validityPeriod": null
    },
    {
      "code": "FLAMABLES.TST22",
      "name": "Firewood Depot",
      "uom": "NUMBEROFDAYS",
      "uomDescription": "Number of Days",
      "applicationDocument": [
        {
          "applicationType": "NEW",
          "documentList": [
            "OWNERIDPROOF",
            "OWNERSHIPPROOF",
            "OWNERPHOTO"
          ]
        },
        {
          "applicationType": "RENEWAL",
          "documentList": [
            "OWNERIDPROOF",
            "OWNERSHIPPROOF",
            "OWNERPHOTO",
            "OLDLICENCENO"
          ]
        }
      ],
      "verificationDocument": [],
      "active": true,
      "type": "TL",
      "validityPeriod": null
    },
    {
      "code": "NONEATINGNONMEDICALESTABLISHMENTS.TST266",
      "name": "Car Accessories and Music System",
      "uom": "NUMBEROFDAYS",
      "uomDescription": "Number of Days",
      "applicationDocument": [
        {
          "applicationType": "NEW",
          "documentList": [
            "OWNERIDPROOF",
            "OWNERSHIPPROOF",
            "OWNERPHOTO"
          ]
        },
        {
          "applicationType": "RENEWAL",
          "documentList": [
            "OWNERIDPROOF",
            "OWNERSHIPPROOF",
            "OWNERPHOTO",
            "OLDLICENCENO"
          ]
        }
      ],
      "verificationDocument": [],
      "active": true,
      "type": "TL",
      "validityPeriod": null
    },
    {
      "code": "NONEATINGNONMEDICALESTABLISHMENTS.TST298",
      "name": "Fabrication Work Shop",
      "uom": "NUMBEROFDAYS",
      "uomDescription": "Number of Days",
      "applicationDocument": [
        {
          "applicationType": "NEW",
          "documentList": [
            "OWNERIDPROOF",
            "OWNERSHIPPROOF",
            "OWNERPHOTO"
          ]
        },
        {
          "applicationType": "RENEWAL",
          "documentList": [
            "OWNERIDPROOF",
            "OWNERSHIPPROOF",
            "OWNERPHOTO",
            "OLDLICENCENO"
          ]
        }
      ],
      "verificationDocument": [],
      "active": true,
      "type": "TL",
      "validityPeriod": null
    },
    {
      "code": "EATINGESTABLISHMENTS.TST36",
      "name": "Omfed/opolfed",
      "uom": "NUMBEROFDAYS",
      "uomDescription": "Number of Days",
      "applicationDocument": [
        {
          "applicationType": "NEW",
          "documentList": [
            "OWNERIDPROOF",
            "OWNERSHIPPROOF",
            "OWNERPHOTO"
          ]
        },
        {
          "applicationType": "RENEWAL",
          "documentList": [
            "OWNERIDPROOF",
            "OWNERSHIPPROOF",
            "OWNERPHOTO",
            "OLDLICENCENO"
          ]
        }
      ],
      "verificationDocument": [],
      "active": true,
      "type": "TL",
      "validityPeriod": null
    },
    {
      "code": "NONEATINGNONMEDICALESTABLISHMENTS.TST447",
      "name": "Wholesale Distributor soft drink",
      "uom": "NUMBEROFDAYS",
      "uomDescription": "Number of Days",
      "applicationDocument": [
        {
          "applicationType": "NEW",
          "documentList": [
            "OWNERIDPROOF",
            "OWNERSHIPPROOF",
            "OWNERPHOTO"
          ]
        },
        {
          "applicationType": "RENEWAL",
          "documentList": [
            "OWNERIDPROOF",
            "OWNERSHIPPROOF",
            "OWNERPHOTO",
            "OLDLICENCENO"
          ]
        }
      ],
      "verificationDocument": [],
      "active": true,
      "type": "TL",
      "validityPeriod": null
    },
    {
      "code": "NONEATINGNONMEDICALESTABLISHMENTS.TST288",
      "name": "Digital Flex Banner",
      "uom": "NUMBEROFDAYS",
      "uomDescription": "Number of Days",
      "applicationDocument": [
        {
          "applicationType": "NEW",
          "documentList": [
            "OWNERIDPROOF",
            "OWNERSHIPPROOF",
            "OWNERPHOTO"
          ]
        },
        {
          "applicationType": "RENEWAL",
          "documentList": [
            "OWNERIDPROOF",
            "OWNERSHIPPROOF",
            "OWNERPHOTO",
            "OLDLICENCENO"
          ]
        }
      ],
      "verificationDocument": [],
      "active": true,
      "type": "TL",
      "validityPeriod": null
    },
    {
      "code": "NONEATINGNONMEDICALESTABLISHMENTS.TST335",
      "name": "Lime",
      "uom": "NUMBEROFDAYS",
      "uomDescription": "Number of Days",
      "applicationDocument": [
        {
          "applicationType": "NEW",
          "documentList": [
            "OWNERIDPROOF",
            "OWNERSHIPPROOF",
            "OWNERPHOTO"
          ]
        },
        {
          "applicationType": "RENEWAL",
          "documentList": [
            "OWNERIDPROOF",
            "OWNERSHIPPROOF",
            "OWNERPHOTO",
            "OLDLICENCENO"
          ]
        }
      ],
      "verificationDocument": [],
      "active": true,
      "type": "TL",
      "validityPeriod": null
    },
    {
      "code": "EATINGESTABLISHMENTS.TST38",
      "name": "Street Food",
      "uom": "NUMBEROFDAYS",
      "uomDescription": "Number of Days",
      "applicationDocument": [
        {
          "applicationType": "NEW",
          "documentList": [
            "OWNERIDPROOF",
            "OWNERSHIPPROOF",
            "OWNERPHOTO"
          ]
        },
        {
          "applicationType": "RENEWAL",
          "documentList": [
            "OWNERIDPROOF",
            "OWNERSHIPPROOF",
            "OWNERPHOTO",
            "OLDLICENCENO"
          ]
        }
      ],
      "verificationDocument": [],
      "active": true,
      "type": "TL",
      "validityPeriod": null
    },
    {
      "code": "NONEATINGNONMEDICALESTABLISHMENTS.TST264",
      "name": "Cabin",
      "uom": "NUMBEROFDAYS",
      "uomDescription": "Number of Days",
      "applicationDocument": [
        {
          "applicationType": "NEW",
          "documentList": [
            "OWNERIDPROOF",
            "OWNERSHIPPROOF",
            "OWNERPHOTO"
          ]
        },
        {
          "applicationType": "RENEWAL",
          "documentList": [
            "OWNERIDPROOF",
            "OWNERSHIPPROOF",
            "OWNERPHOTO",
            "OLDLICENCENO"
          ]
        }
      ],
      "verificationDocument": [],
      "active": true,
      "type": "TL",
      "validityPeriod": null
    },
    {
      "code": "EATINGESTABLISHMENTS.TST39",
      "name": "Wholesaling Mushroom",
      "uom": "NUMBEROFDAYS",
      "uomDescription": "Number of Days",
      "applicationDocument": [
        {
          "applicationType": "NEW",
          "documentList": [
            "OWNERIDPROOF",
            "OWNERSHIPPROOF",
            "OWNERPHOTO"
          ]
        },
        {
          "applicationType": "RENEWAL",
          "documentList": [
            "OWNERIDPROOF",
            "OWNERSHIPPROOF",
            "OWNERPHOTO",
            "OLDLICENCENO"
          ]
        }
      ],
      "verificationDocument": [],
      "active": true,
      "type": "TL",
      "validityPeriod": null
    },
    {
      "code": "NONEATINGNONMEDICALESTABLISHMENTS.TST265",
      "name": "Cane Products",
      "uom": "NUMBEROFDAYS",
      "uomDescription": "Number of Days",
      "applicationDocument": [
        {
          "applicationType": "NEW",
          "documentList": [
            "OWNERIDPROOF",
            "OWNERSHIPPROOF",
            "OWNERPHOTO"
          ]
        },
        {
          "applicationType": "RENEWAL",
          "documentList": [
            "OWNERIDPROOF",
            "OWNERSHIPPROOF",
            "OWNERPHOTO",
            "OLDLICENCENO"
          ]
        }
      ],
      "verificationDocument": [],
      "active": true,
      "type": "TL",
      "validityPeriod": null
    },
    {
      "code": "NONEATINGNONMEDICALESTABLISHMENTS.TST350",
      "name": "Nursery",
      "uom": "NUMBEROFDAYS",
      "uomDescription": "Number of Days",
      "applicationDocument": [
        {
          "applicationType": "NEW",
          "documentList": [
            "OWNERIDPROOF",
            "OWNERSHIPPROOF",
            "OWNERPHOTO"
          ]
        },
        {
          "applicationType": "RENEWAL",
          "documentList": [
            "OWNERIDPROOF",
            "OWNERSHIPPROOF",
            "OWNERPHOTO",
            "OLDLICENCENO"
          ]
        }
      ],
      "verificationDocument": [],
      "active": true,
      "type": "TL",
      "validityPeriod": null
    },
    {
      "code": "NONEATINGNONMEDICALESTABLISHMENTS.TST365",
      "name": "Printing or Embossing Cloth",
      "uom": "NUMBEROFDAYS",
      "uomDescription": "Number of Days",
      "applicationDocument": [
        {
          "applicationType": "NEW",
          "documentList": [
            "OWNERIDPROOF",
            "OWNERSHIPPROOF",
            "OWNERPHOTO"
          ]
        },
        {
          "applicationType": "RENEWAL",
          "documentList": [
            "OWNERIDPROOF",
            "OWNERSHIPPROOF",
            "OWNERPHOTO",
            "OLDLICENCENO"
          ]
        }
      ],
      "verificationDocument": [],
      "active": true,
      "type": "TL",
      "validityPeriod": null
    },
    {
      "code": "LIVESTOCKANDRELATEDPRODUCTS.TST28",
      "name": "Animal/Cattle feed shop",
      "uom": "NUMBEROFDAYS",
      "uomDescription": "Number of Days",
      "applicationDocument": [
        {
          "applicationType": "NEW",
          "documentList": [
            "OWNERIDPROOF",
            "OWNERSHIPPROOF",
            "OWNERPHOTO"
          ]
        },
        {
          "applicationType": "RENEWAL",
          "documentList": [
            "OWNERIDPROOF",
            "OWNERSHIPPROOF",
            "OWNERPHOTO",
            "OLDLICENCENO"
          ]
        }
      ],
      "verificationDocument": [],
      "active": true,
      "type": "TL",
      "validityPeriod": null
    },
    {
      "code": "NONEATINGNONMEDICALESTABLISHMENTS.TST279",
      "name": "Competitive Institute",
      "uom": "NUMBEROFDAYS",
      "uomDescription": "Number of Days",
      "applicationDocument": [
        {
          "applicationType": "NEW",
          "documentList": [
            "OWNERIDPROOF",
            "OWNERSHIPPROOF",
            "OWNERPHOTO"
          ]
        },
        {
          "applicationType": "RENEWAL",
          "documentList": [
            "OWNERIDPROOF",
            "OWNERSHIPPROOF",
            "OWNERPHOTO",
            "OLDLICENCENO"
          ]
        }
      ],
      "verificationDocument": [],
      "active": true,
      "type": "TL",
      "validityPeriod": null
    },
    {
      "code": "NONEATINGNONMEDICALESTABLISHMENTS.TST338",
      "name": "Lubricants",
      "uom": "NUMBEROFDAYS",
      "uomDescription": "Number of Days",
      "applicationDocument": [
        {
          "applicationType": "NEW",
          "documentList": [
            "OWNERIDPROOF",
            "OWNERSHIPPROOF",
            "OWNERPHOTO"
          ]
        },
        {
          "applicationType": "RENEWAL",
          "documentList": [
            "OWNERIDPROOF",
            "OWNERSHIPPROOF",
            "OWNERPHOTO",
            "OLDLICENCENO"
          ]
        }
      ],
      "verificationDocument": [],
      "active": true,
      "type": "TL",
      "validityPeriod": null
    },
    {
      "code": "NONEATINGNONMEDICALESTABLISHMENTS.TST290",
      "name": "Driving Training Centre",
      "uom": "NUMBEROFDAYS",
      "uomDescription": "Number of Days",
      "applicationDocument": [
        {
          "applicationType": "NEW",
          "documentList": [
            "OWNERIDPROOF",
            "OWNERSHIPPROOF",
            "OWNERPHOTO"
          ]
        },
        {
          "applicationType": "RENEWAL",
          "documentList": [
            "OWNERIDPROOF",
            "OWNERSHIPPROOF",
            "OWNERPHOTO",
            "OLDLICENCENO"
          ]
        }
      ],
      "verificationDocument": [],
      "active": true,
      "type": "TL",
      "validityPeriod": null
    },
    {
      "code": "NONEATINGNONMEDICALESTABLISHMENTS.TST244",
      "name": "Almond Storage and Selling",
      "uom": "NUMBEROFDAYS",
      "uomDescription": "Number of Days",
      "applicationDocument": [
        {
          "applicationType": "NEW",
          "documentList": [
            "OWNERIDPROOF",
            "OWNERSHIPPROOF",
            "OWNERPHOTO"
          ]
        },
        {
          "applicationType": "RENEWAL",
          "documentList": [
            "OWNERIDPROOF",
            "OWNERSHIPPROOF",
            "OWNERPHOTO",
            "OLDLICENCENO"
          ]
        }
      ],
      "verificationDocument": [],
      "active": true,
      "type": "TL",
      "validityPeriod": null
    },
    {
      "code": "FLAMABLES.TST19",
      "name": "Acetylene Gas",
      "uom": "NUMBEROFDAYS",
      "uomDescription": "Number of Days",
      "applicationDocument": [
        {
          "applicationType": "NEW",
          "documentList": [
            "OWNERIDPROOF",
            "OWNERSHIPPROOF",
            "OWNERPHOTO"
          ]
        },
        {
          "applicationType": "RENEWAL",
          "documentList": [
            "OWNERIDPROOF",
            "OWNERSHIPPROOF",
            "OWNERPHOTO",
            "OLDLICENCENO"
          ]
        }
      ],
      "verificationDocument": [],
      "active": true,
      "type": "TL",
      "validityPeriod": null
    },
    {
      "code": "NONEATINGNONMEDICALESTABLISHMENTS.TST285",
      "name": "Cycle Mechanic / repairing",
      "uom": "NUMBEROFDAYS",
      "uomDescription": "Number of Days",
      "applicationDocument": [
        {
          "applicationType": "NEW",
          "documentList": [
            "OWNERIDPROOF",
            "OWNERSHIPPROOF",
            "OWNERPHOTO"
          ]
        },
        {
          "applicationType": "RENEWAL",
          "documentList": [
            "OWNERIDPROOF",
            "OWNERSHIPPROOF",
            "OWNERPHOTO",
            "OLDLICENCENO"
          ]
        }
      ],
      "verificationDocument": [],
      "active": true,
      "type": "TL",
      "validityPeriod": null
    },
    {
      "code": "NONEATINGNONMEDICALESTABLISHMENTS.TST243",
      "name": "Agriculture items",
      "uom": "NUMBEROFDAYS",
      "uomDescription": "Number of Days",
      "applicationDocument": [
        {
          "applicationType": "NEW",
          "documentList": [
            "OWNERIDPROOF",
            "OWNERSHIPPROOF",
            "OWNERPHOTO"
          ]
        },
        {
          "applicationType": "RENEWAL",
          "documentList": [
            "OWNERIDPROOF",
            "OWNERSHIPPROOF",
            "OWNERPHOTO",
            "OLDLICENCENO"
          ]
        }
      ],
      "verificationDocument": [],
      "active": true,
      "type": "TL",
      "validityPeriod": null
    },
    {
      "code": "NONEATINGNONMEDICALESTABLISHMENTS.TST366",
      "name": "Private Company/ Profit Making Organisation",
      "uom": "NUMBEROFDAYS",
      "uomDescription": "Number of Days",
      "applicationDocument": [
        {
          "applicationType": "NEW",
          "documentList": [
            "OWNERIDPROOF",
            "OWNERSHIPPROOF",
            "OWNERPHOTO"
          ]
        },
        {
          "applicationType": "RENEWAL",
          "documentList": [
            "OWNERIDPROOF",
            "OWNERSHIPPROOF",
            "OWNERPHOTO",
            "OLDLICENCENO"
          ]
        }
      ],
      "verificationDocument": [],
      "active": true,
      "type": "TL",
      "validityPeriod": null
    },
    {
      "code": "NONEATINGNONMEDICALESTABLISHMENTS.TST421",
      "name": "Tower",
      "uom": "NUMBEROFDAYS",
      "uomDescription": "Number of Days",
      "applicationDocument": [
        {
          "applicationType": "NEW",
          "documentList": [
            "OWNERIDPROOF",
            "OWNERSHIPPROOF",
            "OWNERPHOTO"
          ]
        },
        {
          "applicationType": "RENEWAL",
          "documentList": [
            "OWNERIDPROOF",
            "OWNERSHIPPROOF",
            "OWNERPHOTO",
            "OLDLICENCENO"
          ]
        }
      ],
      "verificationDocument": [],
      "active": true,
      "type": "TL",
      "validityPeriod": null
    },
    {
      "code": "NONEATINGNONMEDICALESTABLISHMENTS.TST262",
      "name": "Burning brick",
      "uom": "NUMBEROFDAYS",
      "uomDescription": "Number of Days",
      "applicationDocument": [
        {
          "applicationType": "NEW",
          "documentList": [
            "OWNERIDPROOF",
            "OWNERSHIPPROOF",
            "OWNERPHOTO"
          ]
        },
        {
          "applicationType": "RENEWAL",
          "documentList": [
            "OWNERIDPROOF",
            "OWNERSHIPPROOF",
            "OWNERPHOTO",
            "OLDLICENCENO"
          ]
        }
      ],
      "verificationDocument": [],
      "active": true,
      "type": "TL",
      "validityPeriod": null
    },
    {
      "code": "NONEATINGNONMEDICALESTABLISHMENTS.TST448",
      "name": "Wholesaler All sorts of Tobacco products",
      "uom": "NUMBEROFDAYS",
      "uomDescription": "Number of Days",
      "applicationDocument": [
        {
          "applicationType": "NEW",
          "documentList": [
            "OWNERIDPROOF",
            "OWNERSHIPPROOF",
            "OWNERPHOTO"
          ]
        },
        {
          "applicationType": "RENEWAL",
          "documentList": [
            "OWNERIDPROOF",
            "OWNERSHIPPROOF",
            "OWNERPHOTO",
            "OLDLICENCENO"
          ]
        }
      ],
      "verificationDocument": [],
      "active": true,
      "type": "TL",
      "validityPeriod": null
    },
    {
      "code": "NONEATINGNONMEDICALESTABLISHMENTS.TST261",
      "name": "Boutique Shop",
      "uom": "NUMBEROFDAYS",
      "uomDescription": "Number of Days",
      "applicationDocument": [
        {
          "applicationType": "NEW",
          "documentList": [
            "OWNERIDPROOF",
            "OWNERSHIPPROOF",
            "OWNERPHOTO"
          ]
        },
        {
          "applicationType": "RENEWAL",
          "documentList": [
            "OWNERIDPROOF",
            "OWNERSHIPPROOF",
            "OWNERPHOTO",
            "OLDLICENCENO"
          ]
        }
      ],
      "verificationDocument": [],
      "active": true,
      "type": "TL",
      "validityPeriod": null
    },
    {
      "code": "NONEATINGNONMEDICALESTABLISHMENTS.TST413",
      "name": "Tattoo or nail art parlour",
      "uom": "NUMBEROFDAYS",
      "uomDescription": "Number of Days",
      "applicationDocument": [
        {
          "applicationType": "NEW",
          "documentList": [
            "OWNERIDPROOF",
            "OWNERSHIPPROOF",
            "OWNERPHOTO"
          ]
        },
        {
          "applicationType": "RENEWAL",
          "documentList": [
            "OWNERIDPROOF",
            "OWNERSHIPPROOF",
            "OWNERPHOTO",
            "OLDLICENCENO"
          ]
        }
      ],
      "verificationDocument": [],
      "active": true,
      "type": "TL",
      "validityPeriod": null
    },
    {
      "code": "NONEATINGNONMEDICALESTABLISHMENTS.TST304",
      "name": "Food Grain",
      "uom": "NUMBEROFDAYS",
      "uomDescription": "Number of Days",
      "applicationDocument": [
        {
          "applicationType": "NEW",
          "documentList": [
            "OWNERIDPROOF",
            "OWNERSHIPPROOF",
            "OWNERPHOTO"
          ]
        },
        {
          "applicationType": "RENEWAL",
          "documentList": [
            "OWNERIDPROOF",
            "OWNERSHIPPROOF",
            "OWNERPHOTO",
            "OLDLICENCENO"
          ]
        }
      ],
      "verificationDocument": [],
      "active": true,
      "type": "TL",
      "validityPeriod": null
    },
    {
      "code": "MEDICALESTABLISHMENTS.TST11",
      "name": "Blood Bank",
      "uom": "NUMBEROFDAYS",
      "uomDescription": "Number of Days",
      "applicationDocument": [
        {
          "applicationType": "NEW",
          "documentList": [
            "OWNERIDPROOF",
            "OWNERSHIPPROOF",
            "OWNERPHOTO"
          ]
        },
        {
          "applicationType": "RENEWAL",
          "documentList": [
            "OWNERIDPROOF",
            "OWNERSHIPPROOF",
            "OWNERPHOTO",
            "OLDLICENCENO"
          ]
        }
      ],
      "verificationDocument": [],
      "active": true,
      "type": "TL",
      "validityPeriod": null
    },
    {
      "code": "EATINGESTABLISHMENTS.TST30",
      "name": "Dhaba",
      "uom": "NUMBEROFDAYS",
      "uomDescription": "Number of Days",
      "applicationDocument": [
        {
          "applicationType": "NEW",
          "documentList": [
            "OWNERIDPROOF",
            "OWNERSHIPPROOF",
            "OWNERPHOTO"
          ]
        },
        {
          "applicationType": "RENEWAL",
          "documentList": [
            "OWNERIDPROOF",
            "OWNERSHIPPROOF",
            "OWNERPHOTO",
            "OLDLICENCENO"
          ]
        }
      ],
      "verificationDocument": [],
      "active": true,
      "type": "TL",
      "validityPeriod": null
    },
    {
      "code": "NONEATINGNONMEDICALESTABLISHMENTS.TST260",
      "name": "Book Publication",
      "uom": "NUMBEROFDAYS",
      "uomDescription": "Number of Days",
      "applicationDocument": [
        {
          "applicationType": "NEW",
          "documentList": [
            "OWNERIDPROOF",
            "OWNERSHIPPROOF",
            "OWNERPHOTO"
          ]
        },
        {
          "applicationType": "RENEWAL",
          "documentList": [
            "OWNERIDPROOF",
            "OWNERSHIPPROOF",
            "OWNERPHOTO",
            "OLDLICENCENO"
          ]
        }
      ],
      "verificationDocument": [],
      "active": true,
      "type": "TL",
      "validityPeriod": null
    },
    {
      "code": "MEDICALESTABLISHMENTS.TST12",
      "name": "Dental Clinic",
      "uom": "NUMBEROFDAYS",
      "uomDescription": "Number of Days",
      "applicationDocument": [
        {
          "applicationType": "NEW",
          "documentList": [
            "OWNERIDPROOF",
            "OWNERSHIPPROOF",
            "OWNERPHOTO"
          ]
        },
        {
          "applicationType": "RENEWAL",
          "documentList": [
            "OWNERIDPROOF",
            "OWNERSHIPPROOF",
            "OWNERPHOTO",
            "OLDLICENCENO"
          ]
        }
      ],
      "verificationDocument": [],
      "active": true,
      "type": "TL",
      "validityPeriod": null
    },
    {
      "code": "MEDICALESTABLISHMENTS.TST13",
      "name": "Drug Wholesale distributer",
      "uom": "NUMBEROFDAYS",
      "uomDescription": "Number of Days",
      "applicationDocument": [
        {
          "applicationType": "NEW",
          "documentList": [
            "OWNERIDPROOF",
            "OWNERSHIPPROOF",
            "OWNERPHOTO"
          ]
        },
        {
          "applicationType": "RENEWAL",
          "documentList": [
            "OWNERIDPROOF",
            "OWNERSHIPPROOF",
            "OWNERPHOTO",
            "OLDLICENCENO"
          ]
        }
      ],
      "verificationDocument": [],
      "active": true,
      "type": "TL",
      "validityPeriod": null
    },
    {
      "code": "NONEATINGNONMEDICALESTABLISHMENTS.TST422",
      "name": "Tower ( Wireless )",
      "uom": "NUMBEROFDAYS",
      "uomDescription": "Number of Days",
      "applicationDocument": [
        {
          "applicationType": "NEW",
          "documentList": [
            "OWNERIDPROOF",
            "OWNERSHIPPROOF",
            "OWNERPHOTO"
          ]
        },
        {
          "applicationType": "RENEWAL",
          "documentList": [
            "OWNERIDPROOF",
            "OWNERSHIPPROOF",
            "OWNERPHOTO",
            "OLDLICENCENO"
          ]
        }
      ],
      "verificationDocument": [],
      "active": true,
      "type": "TL",
      "validityPeriod": null
    },
    {
      "code": "MEDICALESTABLISHMENTS.TST16",
      "name": "Homeopathy Medicine store",
      "uom": "NUMBEROFDAYS",
      "uomDescription": "Number of Days",
      "applicationDocument": [
        {
          "applicationType": "NEW",
          "documentList": [
            "OWNERIDPROOF",
            "OWNERSHIPPROOF",
            "OWNERPHOTO"
          ]
        },
        {
          "applicationType": "RENEWAL",
          "documentList": [
            "OWNERIDPROOF",
            "OWNERSHIPPROOF",
            "OWNERPHOTO",
            "OLDLICENCENO"
          ]
        }
      ],
      "verificationDocument": [],
      "active": true,
      "type": "TL",
      "validityPeriod": null
    },
    {
      "code": "NONEATINGNONMEDICALESTABLISHMENTS.TST307",
      "name": "Generator And Lights",
      "uom": "NUMBEROFDAYS",
      "uomDescription": "Number of Days",
      "applicationDocument": [
        {
          "applicationType": "NEW",
          "documentList": [
            "OWNERIDPROOF",
            "OWNERSHIPPROOF",
            "OWNERPHOTO"
          ]
        },
        {
          "applicationType": "RENEWAL",
          "documentList": [
            "OWNERIDPROOF",
            "OWNERSHIPPROOF",
            "OWNERPHOTO",
            "OLDLICENCENO"
          ]
        }
      ],
      "verificationDocument": [],
      "active": true,
      "type": "TL",
      "validityPeriod": null
    },
    {
      "code": "NONEATINGNONMEDICALESTABLISHMENTS.TST280",
      "name": "Computer Education",
      "uom": "NUMBEROFDAYS",
      "uomDescription": "Number of Days",
      "applicationDocument": [
        {
          "applicationType": "NEW",
          "documentList": [
            "OWNERIDPROOF",
            "OWNERSHIPPROOF",
            "OWNERPHOTO"
          ]
        },
        {
          "applicationType": "RENEWAL",
          "documentList": [
            "OWNERIDPROOF",
            "OWNERSHIPPROOF",
            "OWNERPHOTO",
            "OLDLICENCENO"
          ]
        }
      ],
      "verificationDocument": [],
      "active": true,
      "type": "TL",
      "validityPeriod": null
    },
    {
      "code": "NONEATINGNONMEDICALESTABLISHMENTS.TST305",
      "name": "Food Supplements",
      "uom": "NUMBEROFDAYS",
      "uomDescription": "Number of Days",
      "applicationDocument": [
        {
          "applicationType": "NEW",
          "documentList": [
            "OWNERIDPROOF",
            "OWNERSHIPPROOF",
            "OWNERPHOTO"
          ]
        },
        {
          "applicationType": "RENEWAL",
          "documentList": [
            "OWNERIDPROOF",
            "OWNERSHIPPROOF",
            "OWNERPHOTO",
            "OLDLICENCENO"
          ]
        }
      ],
      "verificationDocument": [],
      "active": true,
      "type": "TL",
      "validityPeriod": null
    },
    {
      "code": "NONEATINGNONMEDICALESTABLISHMENTS.TST401",
      "name": "Steel Railing Glass Home Interior",
      "uom": "NUMBEROFDAYS",
      "uomDescription": "Number of Days",
      "applicationDocument": [
        {
          "applicationType": "NEW",
          "documentList": [
            "OWNERIDPROOF",
            "OWNERSHIPPROOF",
            "OWNERPHOTO"
          ]
        },
        {
          "applicationType": "RENEWAL",
          "documentList": [
            "OWNERIDPROOF",
            "OWNERSHIPPROOF",
            "OWNERPHOTO",
            "OLDLICENCENO"
          ]
        }
      ],
      "verificationDocument": [],
      "active": true,
      "type": "TL",
      "validityPeriod": null
    },
    {
      "code": "NONEATINGNONMEDICALESTABLISHMENTS.TST331",
      "name": "Jatra/Circus/Drama/Theatre Company",
      "uom": "NUMBEROFDAYS",
      "uomDescription": "Number of Days",
      "applicationDocument": [
        {
          "applicationType": "NEW",
          "documentList": [
            "OWNERIDPROOF",
            "OWNERSHIPPROOF",
            "OWNERPHOTO"
          ]
        },
        {
          "applicationType": "RENEWAL",
          "documentList": [
            "OWNERIDPROOF",
            "OWNERSHIPPROOF",
            "OWNERPHOTO",
            "OLDLICENCENO"
          ]
        }
      ],
      "verificationDocument": [],
      "active": true,
      "type": "TL",
      "validityPeriod": null
    },
    {
      "code": "NONEATINGNONMEDICALESTABLISHMENTS.TST369",
      "name": "Puffed Rice Mill (Mudhi)",
      "uom": "NUMBEROFDAYS",
      "uomDescription": "Number of Days",
      "applicationDocument": [
        {
          "applicationType": "NEW",
          "documentList": [
            "OWNERIDPROOF",
            "OWNERSHIPPROOF",
            "OWNERPHOTO"
          ]
        },
        {
          "applicationType": "RENEWAL",
          "documentList": [
            "OWNERIDPROOF",
            "OWNERSHIPPROOF",
            "OWNERPHOTO",
            "OLDLICENCENO"
          ]
        }
      ],
      "verificationDocument": [],
      "active": true,
      "type": "TL",
      "validityPeriod": null
    },
    {
      "code": "NONEATINGNONMEDICALESTABLISHMENTS.TST311",
      "name": "Glass Shop",
      "uom": "NUMBEROFDAYS",
      "uomDescription": "Number of Days",
      "applicationDocument": [
        {
          "applicationType": "NEW",
          "documentList": [
            "OWNERIDPROOF",
            "OWNERSHIPPROOF",
            "OWNERPHOTO"
          ]
        },
        {
          "applicationType": "RENEWAL",
          "documentList": [
            "OWNERIDPROOF",
            "OWNERSHIPPROOF",
            "OWNERPHOTO",
            "OLDLICENCENO"
          ]
        }
      ],
      "verificationDocument": [],
      "active": true,
      "type": "TL",
      "validityPeriod": null
    },
    {
      "code": "NONEATINGNONMEDICALESTABLISHMENTS.TST299",
      "name": "Fancy Store",
      "uom": "NUMBEROFDAYS",
      "uomDescription": "Number of Days",
      "applicationDocument": [
        {
          "applicationType": "NEW",
          "documentList": [
            "OWNERIDPROOF",
            "OWNERSHIPPROOF",
            "OWNERPHOTO"
          ]
        },
        {
          "applicationType": "RENEWAL",
          "documentList": [
            "OWNERIDPROOF",
            "OWNERSHIPPROOF",
            "OWNERPHOTO",
            "OLDLICENCENO"
          ]
        }
      ],
      "verificationDocument": [],
      "active": true,
      "type": "TL",
      "validityPeriod": null
    },
    {
      "code": "NONEATINGNONMEDICALESTABLISHMENTS.TST259",
      "name": "Bones",
      "uom": "NUMBEROFDAYS",
      "uomDescription": "Number of Days",
      "applicationDocument": [
        {
          "applicationType": "NEW",
          "documentList": [
            "OWNERIDPROOF",
            "OWNERSHIPPROOF",
            "OWNERPHOTO"
          ]
        },
        {
          "applicationType": "RENEWAL",
          "documentList": [
            "OWNERIDPROOF",
            "OWNERSHIPPROOF",
            "OWNERPHOTO",
            "OLDLICENCENO"
          ]
        }
      ],
      "verificationDocument": [],
      "active": true,
      "type": "TL",
      "validityPeriod": null
    },
    {
      "code": "NONEATINGNONMEDICALESTABLISHMENTS.TST318",
      "name": "Holi or Rangoli shop",
      "uom": "NUMBEROFDAYS",
      "uomDescription": "Number of Days",
      "applicationDocument": [
        {
          "applicationType": "NEW",
          "documentList": [
            "OWNERIDPROOF",
            "OWNERSHIPPROOF",
            "OWNERPHOTO"
          ]
        },
        {
          "applicationType": "RENEWAL",
          "documentList": [
            "OWNERIDPROOF",
            "OWNERSHIPPROOF",
            "OWNERPHOTO",
            "OLDLICENCENO"
          ]
        }
      ],
      "verificationDocument": [],
      "active": true,
      "type": "TL",
      "validityPeriod": null
    }
  ]
}
